monkeypatching/__init__.py
monkeypatching/_monkeypatching.py
monkeypatching/py.typed
monkeypatching/version.py
monkeypatching-0.2.0.dist-info/LICENSE
monkeypatching-0.2.0.dist-info/METADATA
monkeypatching-0.2.0.dist-info/WHEEL
monkeypatching-0.2.0.dist-info/top_level.txt
monkeypatching-0.2.0.dist-info/RECORD
