Metadata-Version: 2.1
Name: monkeypatching
Version: 0.2.0
Summary: A Python package designed for temporary recursive monkeypatching.
Home-page: https://github.com/autoactuary/monkeypatching
Author: Auto Actuary
Classifier: Programming Language :: Python :: 3
Classifier: License :: OSI Approved :: MIT License
Classifier: Operating System :: OS Independent
Requires-Python: >=3.6
License-File: LICENSE
